Metadata-Version: 2.4
Name: bm25s-j
Version: 0.2.0
Summary: Japanese version of bm25s.
Requires-Python: >=3.8
License-File: LICENSE
Requires-Dist: scipy
Requires-Dist: numpy
Requires-Dist: psutil
Requires-Dist: janome
Provides-Extra: core
Requires-Dist: orjson; extra == "core"
Requires-Dist: tqdm; extra == "core"
Requires-Dist: PyStemmer; extra == "core"
Requires-Dist: numba; extra == "core"
Requires-Dist: janome; extra == "core"
Provides-Extra: stem
Requires-Dist: PyStemmer; extra == "stem"
Provides-Extra: hf
Requires-Dist: huggingface_hub; extra == "hf"
Provides-Extra: dev
Requires-Dist: black; extra == "dev"
Requires-Dist: pytest>=8.0.0; extra == "dev"
Requires-Dist: pytest-cov>=4.1.0; extra == "dev"
Provides-Extra: selection
Requires-Dist: jax[cpu]; extra == "selection"
Provides-Extra: evaluation
Requires-Dist: pytrec_eval; extra == "evaluation"
Provides-Extra: full
Requires-Dist: orjson; extra == "full"
Requires-Dist: tqdm; extra == "full"
Requires-Dist: PyStemmer; extra == "full"
Requires-Dist: numba; extra == "full"
Requires-Dist: janome; extra == "full"
Requires-Dist: huggingface_hub; extra == "full"
Requires-Dist: black; extra == "full"
Requires-Dist: jax[cpu]; extra == "full"
Requires-Dist: pytrec_eval; extra == "full"
Requires-Dist: pytest>=8.0.0; extra == "full"
Requires-Dist: pytest-cov>=4.1.0; extra == "full"
Provides-Extra: unix
Dynamic: license-file
